MANIFEST.in
alignlib_lite.pyx
setup.py
alignlib_lite.egg-info/PKG-INFO
alignlib_lite.egg-info/SOURCES.txt
alignlib_lite.egg-info/dependency_links.txt
alignlib_lite.egg-info/not-zip-safe
alignlib_lite.egg-info/top_level.txt
alignlib_src/Alignandum.cpp
alignlib_src/Alignandum.h
alignlib_src/Alignator.cpp
alignlib_src/Alignator.h
alignlib_src/Alignatum.cpp
alignlib_src/Alignatum.h
alignlib_src/AlignlibBase.cpp
alignlib_src/AlignlibBase.h
alignlib_src/AlignlibDebug.cpp
alignlib_src/AlignlibDebug.h
alignlib_src/AlignlibDefault.cpp
alignlib_src/AlignlibException.cpp
alignlib_src/AlignlibException.h
alignlib_src/AlignlibIndex.cpp
alignlib_src/AlignlibIndex.h
alignlib_src/AlignlibMethods.h
alignlib_src/Alignment.cpp
alignlib_src/Alignment.h
alignlib_src/AlignmentFormat.cpp
alignlib_src/AlignmentFormat.h
alignlib_src/AlignmentIterator.h
alignlib_src/DistanceMatrix.cpp
alignlib_src/DistanceMatrix.h
alignlib_src/Distor.cpp
alignlib_src/Distor.h
alignlib_src/Encoder.cpp
alignlib_src/Encoder.h
alignlib_src/Fragmentor.cpp
alignlib_src/Fragmentor.h
alignlib_src/HelpersAlignandum.cpp
alignlib_src/HelpersAlignandum.h
alignlib_src/HelpersAlignator.cpp
alignlib_src/HelpersAlignator.h
alignlib_src/HelpersAlignatum.cpp
alignlib_src/HelpersAlignatum.h
alignlib_src/HelpersAlignment.cpp
alignlib_src/HelpersAlignment.h
alignlib_src/HelpersDistanceMatrix.cpp
alignlib_src/HelpersDistanceMatrix.h
alignlib_src/HelpersDistor.cpp
alignlib_src/HelpersDistor.h
alignlib_src/HelpersEncoder.cpp
alignlib_src/HelpersEncoder.h
alignlib_src/HelpersFragmentor.cpp
alignlib_src/HelpersFragmentor.h
alignlib_src/HelpersIterator2D.cpp
alignlib_src/HelpersIterator2D.h
alignlib_src/HelpersLogOddor.cpp
alignlib_src/HelpersLogOddor.h
alignlib_src/HelpersMultAlignment.cpp
alignlib_src/HelpersMultAlignment.h
alignlib_src/HelpersMultipleAlignator.cpp
alignlib_src/HelpersMultipleAlignator.h
alignlib_src/HelpersMultipleAlignment.cpp
alignlib_src/HelpersMultipleAlignment.h
alignlib_src/HelpersPalette.cpp
alignlib_src/HelpersPalette.h
alignlib_src/HelpersProfile.cpp
alignlib_src/HelpersRegularizor.cpp
alignlib_src/HelpersRegularizor.h
alignlib_src/HelpersScorer.cpp
alignlib_src/HelpersScorer.h
