Metadata-Version: 1.0
Name: alignlib-lite
Version: 0.2.3
Summary: alignlib-lite - simple wrapper around alignlib C++ library for sequence alignment
Home-page: http://sourceforge.net/projects/alignlib/
Author: Andreas Heger
Author-email: andreas.heger@gmail.com
License: BSD
Keywords: Sequence alignment
Platform: any
Classifier: Development Status :: 3 - Alpha
Classifier: Intended Audience :: Science/Research
Classifier: Intended Audience :: Developers
Classifier: License :: OSI Approved
Classifier: Programming Language :: Python
Classifier: Topic :: Software Development
Classifier: Topic :: Scientific/Engineering
Classifier: Operating System :: Microsoft :: Windows
Classifier: Operating System :: POSIX
Classifier: Operating System :: Unix
Classifier: Operating System :: MacOS
